{
  "17896441": [
    "/17896441.756bef52.js"
  ],
  "main": [
    "/main.3133de09.js"
  ],
  "121d2a59": [
    "/121d2a59.431cb726.js"
  ],
  "1be78505": [
    "/1be78505.6a449d33.js"
  ],
  "1ca9f356": [
    "/1ca9f356.e0f78bb5.js"
  ],
  "37efb314": [
    "/37efb314.702b0e6a.js"
  ],
  "46703f94": [
    "/46703f94.82560338.js"
  ],
  "4fc8e5ea": [
    "/4fc8e5ea.3ed8cebc.js"
  ],
  "57d941a4": [
    "/57d941a4.7a038ec5.js"
  ],
  "5b27ad36": [
    "/5b27ad36.054071ad.js"
  ],
  "66dd989e": [
    "/66dd989e.5ae7932b.js"
  ],
  "7095af98": [
    "/7095af98.9fc633d0.js"
  ],
  "81704dbe": [
    "/81704dbe.cc0b5c3b.js"
  ],
  "8b772b5c": [
    "/8b772b5c.b7ac4589.js"
  ],
  "942ffe5e": [
    "/942ffe5e.8103b745.js"
  ],
  "9c9e4252": [
    "/9c9e4252.1e62e12f.js"
  ],
  "9f3e32d5": [
    "/9f3e32d5.16a4dc53.js"
  ],
  "b6d8a4bb": [
    "/b6d8a4bb.b048a004.js"
  ],
  "bbc52011": [
    "/bbc52011.0a4f7ef5.js"
  ],
  "c80c675b": [
    "/c80c675b.3374f900.js"
  ],
  "d04ae2ec": [
    "/d04ae2ec.50373ae3.js"
  ],
  "d09b4859": [
    "/d09b4859.4711e536.js"
  ],
  "d54ded5f": [
    "/d54ded5f.64446b64.js"
  ],
  "d6d15183": [
    "/d6d15183.c26fe0ba.js"
  ],
  "dc5f160a": [
    "/dc5f160a.32ef1e47.js"
  ],
  "e7b6bb1e": [
    "/e7b6bb1e.a0783440.js"
  ],
  "ece76bd1": [
    "/ece76bd1.d14d97ad.js"
  ],
  "f395e7cf": [
    "/f395e7cf.c491d122.js"
  ],
  "f62180bf": [
    "/f62180bf.27921310.js"
  ],
  "ff3a68c4": [
    "/ff3a68c4.bd96e0cc.js"
  ]
}